j2tmpl/__init__.py
j2tmpl/cli.py
j2tmpl-0.1.0.dist-info/licenses/LICENSE.txt
j2tmpl-0.1.0.dist-info/METADATA
j2tmpl-0.1.0.dist-info/WHEEL
j2tmpl-0.1.0.dist-info/entry_points.txt
j2tmpl-0.1.0.dist-info/top_level.txt
j2tmpl-0.1.0.dist-info/RECORD
