Metadata-Version: 2.4
Name: j2tmpl
Version: 0.1.0
Summary: Jinja2 templating based on environment variables.
Author-email: Ilya Kogan <kogan@ohio.edu>
License-Expression: BSD-3-Clause
Project-URL: Homepage, https://github.com/ikogan/j2tmpl
Classifier: Development Status :: 5 - Production/Stable
Classifier: Intended Audience :: Developers
Classifier: Intended Audience :: System Administrators
Classifier: Operating System :: OS Independent
Classifier: Topic :: Software Development
Classifier: Programming Language :: Python :: 3.14
Requires-Python: >=3.14
License-File: LICENSE.txt
Requires-Dist: jinja2~=3.1.6
Provides-Extra: tests
Requires-Dist: pytest~=9.0.1; extra == "tests"
Requires-Dist: flake8~=7.3.0; extra == "tests"
Requires-Dist: pytest-cov~=7.0.0; extra == "tests"
Requires-Dist: pytest-flake8~=1.3.0; extra == "tests"
Requires-Dist: flake8-pyproject~=1.2.0; extra == "tests"
Provides-Extra: build
Requires-Dist: pyinstaller~=6.16.0; extra == "build"
Requires-Dist: build~=1.3.0; extra == "build"
Dynamic: license-file
